candie
main
