Metadata-Version: 2.2
Name: candie.kit
Version: 1.5.1
Summary: A CLI Build tool for C/C++ Projects
Home-page: https://github.com/yashtajne/candie
Author: Yash Tajne
License: Apache 2.0
Classifier: Programming Language :: Python :: 3
Classifier: License :: OSI Approved :: Apache Software License
Classifier: Operating System :: OS Independent
Requires-Python: >=3.6
License-File: LICENSE
Requires-Dist: typer
Requires-Dist: pkgconfig
Requires-Dist: requests
Dynamic: author
Dynamic: classifier
Dynamic: description
Dynamic: description-content-type
Dynamic: home-page
Dynamic: license
Dynamic: requires-dist
Dynamic: requires-python
Dynamic: summary
